sanic_session_spf/__init__.py
sanic_session_spf/plugin.py
Sanic_Session_SPF-0.5.1.post1.dist-info/LICENSE
Sanic_Session_SPF-0.5.1.post1.dist-info/METADATA
Sanic_Session_SPF-0.5.1.post1.dist-info/WHEEL
Sanic_Session_SPF-0.5.1.post1.dist-info/top_level.txt
Sanic_Session_SPF-0.5.1.post1.dist-info/RECORD
